{
  "id": 1070,
  "lastUpdated": "2025-02-27T04:28:36.281Z",
  "agency": "House",
  "description": "Concerning industrial insurance coverage for posttraumatic stress disorders affecting correctional facility workers.",
  "introducedDate": "2025-01-13T08:00:00.000Z",
  "status": "Referred to Appropriations.",
  "actionDate": "2025-02-04T08:00:00.000Z",
  "sponsors": [
    "Davis",
    "Low",
    "Peterson",
    "Griffey",
    "Reeves",
    "Tharinger",
    "Street",
    "Nance",
    "Goodman",
    "Ormsby",
    "Scott",
    "Mena",
    "Macri",
    "Volz",
    "Stonier",
    "Alvarado",
    "Fosse",
    "Doglio",
    "Bernbaum",
    "Ryu",
    "Leavitt",
    "Berry",
    "Eslick",
    "Callan",
    "Obras",
    "Farivar",
    "Timmons",
    "Ortiz-Self",
    "Simmons",
    "Pollet",
    "Duerr",
    "Lekanoff",
    "Salahuddin"
  ],
  "billDocuments": [
    {
      "name": "1070",
      "description": "House Bill 1070",
      "url": "http://lawfilesext.leg.wa.gov/biennium/2025-26/Htm/Bills/House Bills/1070.htm",
      "createdDate": "2024-12-13T20:03:28.700Z"
    },
    {
      "name": "1070-S",
      "description": "Substitute House Bill 1070 as Recommended by Labor & Workplace Standards",
      "url": "http://lawfilesext.leg.wa.gov/biennium/2025-26/Htm/Bills/House Bills/1070-S.htm",
      "createdDate": "2025-02-03T17:16:40.880Z"
    }
  ],
  "billReports": [],
  "billAmendments": []
}